coral_formsets/__init__.py
coral_formsets/apps.py
coral_formsets/static/coral_formsets/js/FormSet.js
coral_formsets/templatetags/__init__.py
coral_formsets/templatetags/coral_formset_tags.py
coral_formsets-0.1.2.dist-info/LICENSE
coral_formsets-0.1.2.dist-info/WHEEL
coral_formsets-0.1.2.dist-info/METADATA
coral_formsets-0.1.2.dist-info/RECORD
