Metadata-Version: 2.1
Name: coral-formsets
Version: 0.1.2
Summary: Coral formsets
Home-page: https://github.com/coral-sistemas/coral-formsets
License: GPL-3.0-only
Keywords: django,formsets,javascript
Author: Cleiton Lima
Author-email: cleiton.limapin@gmail.com
Requires-Python: >=3.7,<4.0
Classifier: Development Status :: 5 - Production/Stable
Classifier: Framework :: Django :: 2.2
Classifier: Framework :: Django :: 3.2
Classifier: Framework :: Django :: 4.0
Classifier: Intended Audience :: Developers
Classifier: License :: OSI Approved :: GNU General Public License v3 (GPLv3)
Classifier: Natural Language :: English
Classifier: Operating System :: OS Independent
Classifier: Programming Language :: Python :: 3
Classifier: Programming Language :: Python :: 3 :: Only
Classifier: Programming Language :: Python :: 3.10
Classifier: Programming Language :: Python :: 3.7
Classifier: Programming Language :: Python :: 3.8
Classifier: Programming Language :: Python :: 3.9
Requires-Dist: Django (>=2.2)
Project-URL: Documentation, https://github.com/coral-sistemas/coral-formsets#coral-formsets
Project-URL: Repository, https://github.com/coral-sistemas/coral-formsets
